assets/assets.png
create_aio_app/__init__.py
create_aio_app/constants.py
create_aio_app/main.py
create_aio_app/template/__init__.py
create_aio_app/template/cookiecutter.json
create_aio_app/template/hooks/post_gen_project.py
create_aio_app/template/hooks/pre_gen_project.py
create_aio_app/template/{{cookiecutter.project_name}}/.gitignore
create_aio_app/template/{{cookiecutter.project_name}}/Dockerfile
create_aio_app/template/{{cookiecutter.project_name}}/Makefile
create_aio_app/template/{{cookiecutter.project_name}}/README.md
create_aio_app/template/{{cookiecutter.project_name}}/alembic.ini
create_aio_app/template/{{cookiecutter.project_name}}/conftest.py
create_aio_app/template/{{cookiecutter.project_name}}/docker-compose.yml
create_aio_app/template/{{cookiecutter.project_name}}/mypy.ini
create_aio_app/template/{{cookiecutter.project_name}}/setup.py
create_aio_app/template/{{cookiecutter.project_name}}/config/api.dev.yml
create_aio_app/template/{{cookiecutter.project_name}}/config/api.prod.yml
create_aio_app/template/{{cookiecutter.project_name}}/config/api.test.yml
create_aio_app/template/{{cookiecutter.project_name}}/docs/Makefile
create_aio_app/template/{{cookiecutter.project_name}}/docs/make.bat
create_aio_app/template/{{cookiecutter.project_name}}/docs/source/conf.py
create_aio_app/template/{{cookiecutter.project_name}}/docs/source/index.rst
create_aio_app/template/{{cookiecutter.project_name}}/docs/source/pages/aiohttp_quick_start.rst
create_aio_app/template/{{cookiecutter.project_name}}/docs/source/pages/commands.rst
create_aio_app/template/{{cookiecutter.project_name}}/docs/source/pages/documentation.rst
create_aio_app/template/{{cookiecutter.project_name}}/docs/source/pages/tests.rst
create_aio_app/template/{{cookiecutter.project_name}}/docs/source/project/.gitkeep
create_aio_app/template/{{cookiecutter.project_name}}/requirements/development.txt
create_aio_app/template/{{cookiecutter.project_name}}/requirements/documentation.txt
create_aio_app-0.0.11.dist-info/LICENSE
create_aio_app-0.0.11.dist-info/METADATA
create_aio_app-0.0.11.dist-info/WHEEL
create_aio_app-0.0.11.dist-info/entry_points.txt
create_aio_app-0.0.11.dist-info/top_level.txt
create_aio_app-0.0.11.dist-info/zip-safe
create_aio_app-0.0.11.dist-info/RECORD
