Metadata-Version: 2.1
Name: create-aio-app
Version: 0.0.11
Summary: The tool that helps quickly create a basis for aiohttp application
Home-page: https://github.com/aio-libs/create-aio-app
Author: Mykhailo Havelia
Author-email: misha.gavela@gmail.com
License: MIT
Project-URL: Source Code, https://github.com/aio-libs/create-aio-app
Project-URL: GitHub Issues, https://github.com/aio-libs/create-aio-app/issues
Project-URL: Documentation, https://create-aio-app.readthedocs.io/
Project-URL: CI: Travis, https://travis-ci.com/aio-libs/create-aio-app
Keywords: create-aio-app,cookiecutter==1.7.3,aiohttp
Platform: POSIX
Classifier: License :: OSI Approved :: MIT License
Classifier: Intended Audience :: Developers
Classifier: Programming Language :: Python :: 3
Classifier: Programming Language :: Python :: 3.6
Classifier: Programming Language :: Python :: 3.7
Classifier: Programming Language :: Python :: 3.8
Classifier: Operating System :: POSIX
Classifier: Development Status :: 4 - Beta
Classifier: Framework :: AsyncIO
Requires-Python: >=3.6
License-File: LICENSE
Requires-Dist: cookiecutter (==1.7.3)
Requires-Dist: click (>=7.0)
